MAMPSQLImport/__init__.py
MAMPSQLImport/configs.py
MAMPSQLImport/functions.py
MAMPSQLImport/main.py
mamp_sql_import-1.0.0.dist-info/LICENSE.txt
mamp_sql_import-1.0.0.dist-info/METADATA
mamp_sql_import-1.0.0.dist-info/WHEEL
mamp_sql_import-1.0.0.dist-info/entry_points.txt
mamp_sql_import-1.0.0.dist-info/top_level.txt
mamp_sql_import-1.0.0.dist-info/RECORD
